[
	{
		"name": "Sputnik 8K74PS | Sputnik 1",
		"status": "Success",
		"launch_year": "1957",
		"failreason": "",
		"launch_service_provider": "Soviet Space Program",
		"rocket": {
			"name": "Sputnik 8K74PS",
			"family": "Sputnik",
			"full_name": "Sputnik 8K74PS",
			"variant": "8K74PS"
		},
		"mission": {
			"name": "Sputnik 1",
			"description": "First artificial satellite consisting of a 58 cm pressurized aluminium shell containing two 1 W transmitters for a total mass of 83.6 kg.",
			"type": "Test Flight",
			"orbit": "Low Earth Orbit",
			"planet_of_interest": null
		},
		"pad": {
			"name": "1/5",
			"location": {
				"name": "Baikonur Cosmodrome, Republic of Kazakhstan",
				"country_code": "KAZ",
				"total_launch_count": 1522,
				"total_landing_count": 0
			}
		}
	},
	{
		"name": "Sputnik 8K74PS | Sputnik 2",
		"status": "Success",
		"launch_year": "1957",
		"failreason": "",
		"launch_service_provider": "Soviet Space Program",
		"rocket": {
			"name": "Sputnik 8K74PS",
			"family": "Sputnik",
			"full_name": "Sputnik 8K74PS",
			"variant": "8K74PS"
		},
		"mission": {
			"name": "Sputnik 2",
			"description": "Second artificial satellite and first to carry an animal into orbit.",
			"type": "Test Flight",
			"orbit": "Low Earth Orbit",
			"planet_of_interest": null
		},
		"pad": {
			"name": "1/5",
			"location": {
				"name": "Baikonur Cosmodrome, Republic of Kazakhstan",
				"country_code": "KAZ",
				"total_launch_count": 1522,
				"total_landing_count": 0
			}
		}
	}
]